carapiparser/__init__.py
carapiparser/format_api.py
carapiparser/parser_excel.py
carapiparser-1.1.1.dist-info/METADATA
carapiparser-1.1.1.dist-info/WHEEL
carapiparser-1.1.1.dist-info/top_level.txt
carapiparser-1.1.1.dist-info/RECORD
