Metadata-Version: 2.1
Name: carapiparser
Version: 1.1.1
Summary: parse car api excel config
Home-page: https://github.com/chinaZoulx
Author: zoulx
Author-email: 894919296@qq.com
License: MIT
Platform: all
Classifier: License :: OSI Approved :: MIT License
Requires-Dist: xlrd (>=1.2.0)
